pyabr/__init__.py
pyabr/__main__.py
pyabr/pyabr.zip
pyabr/setup.py
pyabr-2.4.0.dist-info/LICENSE
pyabr-2.4.0.dist-info/METADATA
pyabr-2.4.0.dist-info/WHEEL
pyabr-2.4.0.dist-info/top_level.txt
pyabr-2.4.0.dist-info/RECORD
