Metadata-Version: 2.1
Name: pyabr
Version: 2.4.0
Summary: Python Cloud & OS
Home-page: https://github.com/PyFarsi/pyabr
Author: Mani Jamali
Author-email: manijamali2003@gmail.com
License: UNKNOWN
Platform: UNKNOWN
Classifier: Programming Language :: Python :: 3
Classifier: License :: OSI Approved :: GNU General Public License v3 (GPLv3)
Classifier: Operating System :: POSIX :: Linux
Requires-Python: >=3.7
License-File: LICENSE
Requires-Dist: PyQt5
Requires-Dist: PyQtWebEngine
Requires-Dist: requests
Requires-Dist: cryptography
Requires-Dist: termcolor
Requires-Dist: wget
Requires-Dist: psutil
